Slpapy/Data_reconstruction.py
Slpapy/MZ_ppm_match.py
Slpapy/__init__.py
Slpapy/processing_analyze.py
Slpapy/Spatial_map_pic/Population_ratio.py
Slpapy/Spatial_map_pic/Spatial_map.py
Slpapy/Spatial_map_pic/__init__.py
Slpapy/Spatial_map_pic/_compat.py
Slpapy/Spatial_map_pic/_docs.py
Slpapy/Spatial_map_pic/_rcmod.py
Slpapy/Spatial_map_pic/_settings.py
Slpapy/Spatial_map_pic/_utils.py
Slpapy/Spatial_map_pic/beats.py
Slpapy/Spatial_map_pic/is_constant.py
Slpapy/Spatial_map_pic/logging.py
Slpapy/Spatial_map_pic/palettes.py
Slpapy/Spatial_map_pic/readwrite.py
Slpapy/Spatial_map_pic/scatterplots.py
Slpapy-0.4.18.dist-info/METADATA
Slpapy-0.4.18.dist-info/WHEEL
Slpapy-0.4.18.dist-info/top_level.txt
Slpapy-0.4.18.dist-info/RECORD
