Metadata-Version: 2.1
Name: Slpapy
Version: 0.4.18
Summary: Spatial_lipomic_and_proteomic_analysis
Author: yifan xu
Author-email: xuyifan@westlake.edu.cn
Requires-Dist: scanpy (>=1.9.1)
Requires-Dist: anndata (>=0.8.0)
Requires-Dist: numpy (>=1.23.0)
Requires-Dist: scipy (>=1.9.0)
Requires-Dist: pandas (>=1.5.1)
Requires-Dist: scikit-learn (>=1.2.1)
Requires-Dist: statsmodels (>=0.13.1)
Requires-Dist: leidenalg (>=0.8.7)
